LICENSE
README
setup.py
django_oot.egg-info/PKG-INFO
django_oot.egg-info/SOURCES.txt
django_oot.egg-info/dependency_links.txt
django_oot.egg-info/top_level.txt
oot/__init__.py
oot/models.py
oot/tests.py
oot/urls.py
oot/views.py
oot/templates/render_image.xml
oot/templates/writer_templates.html
oot/templatetags/__init__.py
oot/templatetags/oot_templates.py
oot/tests_media/writertemplate.odt