Metadata-Version: 1.0
Name: django-oot
Version: 0.8.3
Summary: Django application to export content to OpenOffice documents
Home-page: http://tracpub.yaco.es/djangoapps/wiki/OOT
Author: Yaco Sistemas S.L.
Author-email: precio@yaco.es
License: LGPL 3
Keywords: django openoffice odt
Platform: UNKNOWN
Classifier: Development Status :: 4 - Beta
Classifier: Framework :: Django
Classifier: License :: OSI Approved :: GNU General Public License (GPL)
Classifier: Topic :: Office/Business :: Office Suites
